arducomm/__init__.py
arducomm/arducomm.py
arducomm/serialization/__init__.py
arducomm/serialization/serialization.py
arducomm/types/__init__.py
arducomm/types/float_array.py
arducomm/types/imu.py
arducomm/types/pose.py
arducomm/types/pose2d.py
arducomm/types/quaternion.py
arducomm/types/vector2.py
arducomm/types/vector3.py
arducomm-0.1.0.dist-info/METADATA
arducomm-0.1.0.dist-info/WHEEL
arducomm-0.1.0.dist-info/top_level.txt
arducomm-0.1.0.dist-info/RECORD
