Metadata-Version: 2.1
Name: arducomm
Version: 0.1.0
Summary: A library to enable robust communication between an Arduino and a host via serial
Author-email: Francisco Miguel Moreno <butakus@gmail.com>
Maintainer-email: Francisco Miguel Moreno <butakus@gmail.com>
License: GLPv3
Project-URL: Source, https://github.com/butakus/arducomm
Keywords: communication,arduino,serial
Classifier: Development Status :: 3 - Alpha
Classifier: Intended Audience :: Developers
Classifier: Topic :: Terminals :: Serial
Classifier: Topic :: Communications
Classifier: Topic :: Software Development :: Libraries
Classifier: License :: OSI Approved :: GNU General Public License v3 (GPLv3)
Classifier: Programming Language :: Python :: 3
Classifier: Programming Language :: Python :: 3.7
Classifier: Programming Language :: Python :: 3.8
Classifier: Programming Language :: Python :: 3.9
Classifier: Programming Language :: Python :: 3.10
Classifier: Programming Language :: Python :: 3.11
Classifier: Programming Language :: Python :: 3 :: Only
Requires-Python: >=3.7
Requires-Dist: pyserial
